bossbrain/__init__.py
bossbrain/ann.py
bossbrain/fitting.py
bossbrain/monte.py
bossbrain/monte4.py
bossbrain/utils.py
bossbrain/data/ann_22pars_3500-4200.pkl
bossbrain/data/ann_22pars_4000-5000.pkl
bossbrain/data/ann_22pars_4900-6000.pkl
bossbrain/data/apogeedr17_rgb_feh_ann.npz
bossbrain/data/apogeedr17_rgb_logg_ann.npz
bossbrain/data/spec-3586-55181-0500.fits
bossbrain-1.0.5.data/scripts/bossbrain
bossbrain-1.0.5.dist-info/licenses/LICENSE
bossbrain-1.0.5.dist-info/METADATA
bossbrain-1.0.5.dist-info/WHEEL
bossbrain-1.0.5.dist-info/top_level.txt
bossbrain-1.0.5.dist-info/RECORD
